{
    "Version": 1,
    "Name": "Ver.7",
    "ModelID": "771209a333f74392b3a3181ca5cf789e",
    "FileReferences": {
        "Icon": "",
        "Model": "Ver.7.model3.json",
        "IdleAnimation": "daiji1.motion3.json",
        "IdleAnimationWhenTrackingLost": ""
    },
    "ModelSaveMetadata": {
        "LastSavedVTubeStudioVersion": "1.26.11",
        "LastSavedPlatform": "Steam",
        "LastSavedDateUTC": "Friday, 28 July 2023, 17:38:42",
        "LastSavedDateLocalTime": "Saturday, 29 July 2023, 01:38:42",
        "LastSavedDateUnixMillisecondTimestamp": "1690565922464"
    },
    "SavedModelPosition": {
        "Position": {
            "x": 4.646417617797852,
            "y": -132.57904052734376,
            "z": 0.0
        },
        "Rotation": {
            "x": 0.0,
            "y": 0.0,
            "z": 0.0,
            "w": 1.0
        },
        "Scale": {
            "x": 2.4024136066436769,
            "y": 2.4024136066436769,
            "z": 1.0
        }
    },
    "ModelPositionMovement": {
        "Use": false,
        "X": 0,
        "Y": 0,
        "Z": 0,
        "SmoothingX": 10,
        "SmoothingY": 10,
        "SmoothingZ": 10
    },
    "ItemSettings": {
        "OnlyMoveWhenPinned": false,
        "AllowNormalHotkeyTriggers": true,
        "Multiplier_HeadAngleX": 1.0,
        "Multiplier_HeadAngleY": 1.0,
        "Multiplier_HeadAngleZ": 1.0,
        "Shift_HeadAngleX": 0.0,
        "Shift_HeadAngleY": 0.0,
        "Smoothing_HeadAngleX": 15.0,
        "Smoothing_HeadAngleY": 15.0,
        "Smoothing_HeadAngleZ": 15.0
    },
    "PhysicsSettings": {
        "Use": true,
        "UseLegacyPhysics": false,
        "Live2DPhysicsFPS": 3,
        "PhysicsStrength": 50,
        "WindStrength": 0,
        "DraggingPhysicsStrength": 0
    },
    "GeneralSettings": {
        "TimeUntilTrackingLostIdleAnimation": 0.0,
        "WorkshopSharingForbidden": true,
        "EnableExpressionSaving": false
    },
    "ParameterSettings": [
        {
            "Folder": "",
            "Name": "Face Left/Right Rotation",
            "Input": "FaceAngleX",
            "InputRangeLower": -30.0,
            "InputRangeUpper": 30.0,
            "OutputRangeLower": -30.0,
            "OutputRangeUpper": 30.0,
            "ClampInput": false,
            "ClampOutput": false,
            "UseBlinking": false,
            "UseBreathing": false,
            "OutputLive2D": "ParamAngleX",
            "Smoothing": 15,
            "Minimized": true
        },
        {
            "Folder": "",
            "Name": "Face Up/Down Rotation",
            "Input": "FaceAngleY",
            "InputRangeLower": -20.0,
            "InputRangeUpper": 20.0,
            "OutputRangeLower": -30.0,
            "OutputRangeUpper": 30.0,
            "ClampInput": false,
            "ClampOutput": false,
            "UseBlinking": false,
            "UseBreathing": false,
            "OutputLive2D": "ParamAngleY",
            "Smoothing": 15,
            "Minimized": true
        },
        {
            "Folder": "",
            "Name": "Face Lean Rotation",
            "Input": "FaceAngleZ",
            "InputRangeLower": -30.0,
            "InputRangeUpper": 30.0,
            "OutputRangeLower": -30.0,
            "OutputRangeUpper": 30.0,
            "ClampInput": false,
            "ClampOutput": false,
            "UseBlinking": false,
            "UseBreathing": false,
            "OutputLive2D": "ParamAngleZ",
            "Smoothing": 30,
            "Minimized": true
        },
        {
            "Folder": "",
            "Name": "Eye Open Left",
            "Input": "EyeOpenLeft",
            "InputRangeLower": 0.0,
            "InputRangeUpper": 1.0,
            "OutputRangeLower": 0.0,
            "OutputRangeUpper": 1.899999976158142,
            "ClampInput": false,
            "ClampOutput": false,
            "UseBlinking": false,
            "UseBreathing": false,
            "OutputLive2D": "ParamEyeLOpen",
            "Smoothing": 10,
            "Minimized": true
        },
        {
            "Folder": "",
            "Name": "Eye Smile Left",
            "Input": "MouthSmile",
            "InputRangeLower": 0.0,
            "InputRangeUpper": 1.0,
            "OutputRangeLower": 0.0,
            "OutputRangeUpper": 1.0,
            "ClampInput": false,
            "ClampOutput": false,
            "UseBlinking": false,
            "UseBreathing": false,
            "OutputLive2D": "ParamEyeLSmile",
            "Smoothing": 10,
            "Minimized": true
        },
        {
            "Folder": "",
            "Name": "Eye Open Right",
            "Input": "EyeOpenRight",
            "InputRangeLower": 0.0,
            "InputRangeUpper": 1.0,
            "OutputRangeLower": 0.0,
            "OutputRangeUpper": 1.899999976158142,
            "ClampInput": false,
            "ClampOutput": false,
            "UseBlinking": false,
            "UseBreathing": false,
            "OutputLive2D": "ParamEyeROpen",
            "Smoothing": 10,
            "Minimized": true
        },
        {
            "Folder": "",
            "Name": "Eye Smile Right",
            "Input": "MouthSmile",
            "InputRangeLower": 0.0,
            "InputRangeUpper": 1.0,
            "OutputRangeLower": 0.0,
            "OutputRangeUpper": 1.0,
            "ClampInput": false,
            "ClampOutput": false,
            "UseBlinking": false,
            "UseBreathing": false,
            "OutputLive2D": "ParamEyeRSmile",
            "Smoothing": 10,
            "Minimized": true
        },
        {
            "Folder": "",
            "Name": "Eye X",
            "Input": "EyeRightX",
            "InputRangeLower": -1.0,
            "InputRangeUpper": 1.0,
            "OutputRangeLower": 1.0,
            "OutputRangeUpper": -1.0,
            "ClampInput": false,
            "ClampOutput": false,
            "UseBlinking": false,
            "UseBreathing": false,
            "OutputLive2D": "ParamEyeBallX",
            "Smoothing": 8,
            "Minimized": true
        },
        {
            "Folder": "",
            "Name": "Eye Y",
            "Input": "EyeRightY",
            "InputRangeLower": -1.0,
            "InputRangeUpper": 1.0,
            "OutputRangeLower": -1.0,
            "OutputRangeUpper": 1.0,
            "ClampInput": false,
            "ClampOutput": false,
            "UseBlinking": false,
            "UseBreathing": false,
            "OutputLive2D": "ParamEyeBallY",
            "Smoothing": 8,
            "Minimized": true
        },
        {
            "Folder": "",
            "Name": "Brow Form Left",
            "Input": "Brows",
            "InputRangeLower": 0.0,
            "InputRangeUpper": 1.0,
            "OutputRangeLower": -1.0,
            "OutputRangeUpper": 1.0,
            "ClampInput": false,
            "ClampOutput": false,
            "UseBlinking": false,
            "UseBreathing": false,
            "OutputLive2D": "ParamBrowLForm",
            "Smoothing": 15,
            "Minimized": true
        },
        {
            "Folder": "",
            "Name": "Brow Form Right",
            "Input": "Brows",
            "InputRangeLower": 0.0,
            "InputRangeUpper": 1.0,
            "OutputRangeLower": -1.0,
            "OutputRangeUpper": 1.0,
            "ClampInput": false,
            "ClampOutput": false,
            "UseBlinking": false,
            "UseBreathing": false,
            "OutputLive2D": "ParamBrowRForm",
            "Smoothing": 15,
            "Minimized": true
        },
        {
            "Folder": "",
            "Name": "Mouth Smile",
            "Input": "MouthSmile",
            "InputRangeLower": 0.0,
            "InputRangeUpper": 1.0,
            "OutputRangeLower": -1.0,
            "OutputRangeUpper": 1.0,
            "ClampInput": false,
            "ClampOutput": false,
            "UseBlinking": false,
            "UseBreathing": false,
            "OutputLive2D": "ParamMouthForm",
            "Smoothing": 0,
            "Minimized": true
        },
        {
            "Folder": "",
            "Name": "Mouth Open",
            "Input": "MouthOpen",
            "InputRangeLower": 0.0,
            "InputRangeUpper": 1.0,
            "OutputRangeLower": 0.0,
            "OutputRangeUpper": 2.0999999046325685,
            "ClampInput": false,
            "ClampOutput": false,
            "UseBlinking": false,
            "UseBreathing": false,
            "OutputLive2D": "ParamMouthOpenY",
            "Smoothing": 0,
            "Minimized": true
        },
        {
            "Folder": "",
            "Name": "Blush when smiling",
            "Input": "MouthSmile",
            "InputRangeLower": 0.0,
            "InputRangeUpper": 1.0,
            "OutputRangeLower": 0.5,
            "OutputRangeUpper": 1.0,
            "ClampInput": false,
            "ClampOutput": false,
            "UseBlinking": false,
            "UseBreathing": false,
            "OutputLive2D": "ParamCheek",
            "Smoothing": 45,
            "Minimized": true
        },
        {
            "Folder": "",
            "Name": "Body Rotation X",
            "Input": "FaceAngleX",
            "InputRangeLower": -30.0,
            "InputRangeUpper": 30.0,
            "OutputRangeLower": -10.0,
            "OutputRangeUpper": 10.0,
            "ClampInput": false,
            "ClampOutput": false,
            "UseBlinking": false,
            "UseBreathing": false,
            "OutputLive2D": "ParamBodyAngleX",
            "Smoothing": 20,
            "Minimized": true
        },
        {
            "Folder": "",
            "Name": "Body Rotation Y",
            "Input": "FaceAngleY",
            "InputRangeLower": -30.0,
            "InputRangeUpper": 30.0,
            "OutputRangeLower": -10.0,
            "OutputRangeUpper": 10.0,
            "ClampInput": false,
            "ClampOutput": false,
            "UseBlinking": false,
            "UseBreathing": false,
            "OutputLive2D": "ParamBodyAngleY",
            "Smoothing": 20,
            "Minimized": true
        },
        {
            "Folder": "",
            "Name": "Body Rotation Z",
            "Input": "FaceAngleZ",
            "InputRangeLower": -30.0,
            "InputRangeUpper": 30.0,
            "OutputRangeLower": -10.0,
            "OutputRangeUpper": 10.0,
            "ClampInput": false,
            "ClampOutput": false,
            "UseBlinking": false,
            "UseBreathing": false,
            "OutputLive2D": "ParamBodyAngleZ",
            "Smoothing": 20,
            "Minimized": true
        },
        {
            "Folder": "",
            "Name": "Auto Breath",
            "Input": "",
            "InputRangeLower": 0.0,
            "InputRangeUpper": 1.0,
            "OutputRangeLower": 0.0,
            "OutputRangeUpper": 1.0,
            "ClampInput": false,
            "ClampOutput": false,
            "UseBlinking": false,
            "UseBreathing": true,
            "OutputLive2D": "ParamBreath",
            "Smoothing": 0,
            "Minimized": true
        },
        {
            "Folder": "",
            "Name": "",
            "Input": "MouthX",
            "InputRangeLower": -0.800000011920929,
            "InputRangeUpper": 0.800000011920929,
            "OutputRangeLower": -1.0,
            "OutputRangeUpper": 1.0,
            "ClampInput": false,
            "ClampOutput": false,
            "UseBlinking": false,
            "UseBreathing": false,
            "OutputLive2D": "mouthX",
            "Smoothing": 20,
            "Minimized": false
        },
        {
            "Folder": "",
            "Name": "",
            "Input": "MouthShrug",
            "InputRangeLower": 0.0,
            "InputRangeUpper": 0.20000000298023225,
            "OutputRangeLower": 0.0,
            "OutputRangeUpper": 1.0,
            "ClampInput": false,
            "ClampOutput": false,
            "UseBlinking": false,
            "UseBreathing": false,
            "OutputLive2D": "mouthUP",
            "Smoothing": 20,
            "Minimized": false
        },
        {
            "Folder": "",
            "Name": "",
            "Input": "JawOpen",
            "InputRangeLower": 0.0,
            "InputRangeUpper": 0.6000000238418579,
            "OutputRangeLower": 0.0,
            "OutputRangeUpper": 1.0,
            "ClampInput": false,
            "ClampOutput": false,
            "UseBlinking": false,
            "UseBreathing": false,
            "OutputLive2D": "mouthDOWN",
            "Smoothing": 20,
            "Minimized": false
        }
    ],
    "Hotkeys": [
        {
            "HotkeyID": "7d782a7a91c24cababf6d7816a27207f",
            "Name": "",
            "Action": "ToggleExpression",
            "File": "dai.exp3.json",
            "Folder": "",
            "Position": {
                "X": 0.0,
                "Y": 0.0,
                "Z": 0.0,
                "Rotation": 0.0
            },
            "ColorOverlay": {
                "On": false,
                "IsStaticColor": false,
                "Display": -1,
                "WindowName": "",
                "IncludeLeft": false,
                "IncludeMid": false,
                "IncludeRight": false,
                "BaseValue": 0,
                "OverlayValue": 0,
                "Smoothing": 0,
                "IncludeItems": false,
                "StaticColor": {
                    "r": 0.0,
                    "g": 0.0,
                    "b": 0.0,
                    "a": 1.0
                }
            },
            "ColorScreenMultiplyPreset": {
                "ArtMeshMultiplyAndScreenColors": []
            },
            "HandGestureSettings": {
                "GestureLeft": "",
                "GestureRight": "",
                "GestureCombinator": "AND",
                "AllowMirroredGesture": false,
                "DeactivateExpWhenGestureNotDetected": false,
                "SecondsUntilDetection": 0.5,
                "SecondsDetected": 0.0,
                "PercentDetected": 0.0
            },
            "LoadModelSettings": {
                "LoadAtCurrentPosition": true
            },
            "Triggers": {
                "Trigger1": "N1",
                "Trigger2": "",
                "Trigger3": "",
                "ScreenButton": -1
            },
            "IsGlobal": true,
            "IsActive": true,
            "Minimized": false,
            "StopsOnLastFrame": false,
            "DeactivateAfterKeyUp": false,
            "OnlyLoadOneRandomItem": false,
            "DeactivateAfterSeconds": false,
            "DeactivateAfterSecondsAmount": 10.0,
            "FadeSecondsAmount": 0.5,
            "OnScreenHotkeyColor": {
                "r": 1.0,
                "g": 1.0,
                "b": 1.0,
                "a": 1.0
            }
        },
        {
            "HotkeyID": "41b18d2815a943a0a7f1df8da113518f",
            "Name": "",
            "Action": "ToggleExpression",
            "File": "fen.exp3.json",
            "Folder": "",
            "Position": {
                "X": 0.0,
                "Y": 0.0,
                "Z": 0.0,
                "Rotation": 0.0
            },
            "ColorOverlay": {
                "On": false,
                "IsStaticColor": false,
                "Display": -1,
                "WindowName": "",
                "IncludeLeft": false,
                "IncludeMid": false,
                "IncludeRight": false,
                "BaseValue": 0,
                "OverlayValue": 0,
                "Smoothing": 0,
                "IncludeItems": false,
                "StaticColor": {
                    "r": 0.0,
                    "g": 0.0,
                    "b": 0.0,
                    "a": 1.0
                }
            },
            "ColorScreenMultiplyPreset": {
                "ArtMeshMultiplyAndScreenColors": []
            },
            "HandGestureSettings": {
                "GestureLeft": "",
                "GestureRight": "",
                "GestureCombinator": "AND",
                "AllowMirroredGesture": false,
                "DeactivateExpWhenGestureNotDetected": false,
                "SecondsUntilDetection": 0.5,
                "SecondsDetected": 0.0,
                "PercentDetected": 0.0
            },
            "LoadModelSettings": {
                "LoadAtCurrentPosition": true
            },
            "Triggers": {
                "Trigger1": "N2",
                "Trigger2": "",
                "Trigger3": "",
                "ScreenButton": -1
            },
            "IsGlobal": true,
            "IsActive": true,
            "Minimized": false,
            "StopsOnLastFrame": false,
            "DeactivateAfterKeyUp": false,
            "OnlyLoadOneRandomItem": false,
            "DeactivateAfterSeconds": false,
            "DeactivateAfterSecondsAmount": 10.0,
            "FadeSecondsAmount": 0.5,
            "OnScreenHotkeyColor": {
                "r": 1.0,
                "g": 1.0,
                "b": 1.0,
                "a": 1.0
            }
        },
        {
            "HotkeyID": "9121242d2138414aacb3076ce59c85be",
            "Name": "",
            "Action": "ToggleExpression",
            "File": "hei.exp3.json",
            "Folder": "",
            "Position": {
                "X": 0.0,
                "Y": 0.0,
                "Z": 0.0,
                "Rotation": 0.0
            },
            "ColorOverlay": {
                "On": false,
                "IsStaticColor": false,
                "Display": -1,
                "WindowName": "",
                "IncludeLeft": false,
                "IncludeMid": false,
                "IncludeRight": false,
                "BaseValue": 0,
                "OverlayValue": 0,
                "Smoothing": 0,
                "IncludeItems": false,
                "StaticColor": {
                    "r": 0.0,
                    "g": 0.0,
                    "b": 0.0,
                    "a": 1.0
                }
            },
            "ColorScreenMultiplyPreset": {
                "ArtMeshMultiplyAndScreenColors": []
            },
            "HandGestureSettings": {
                "GestureLeft": "",
                "GestureRight": "",
                "GestureCombinator": "AND",
                "AllowMirroredGesture": false,
                "DeactivateExpWhenGestureNotDetected": false,
                "SecondsUntilDetection": 0.5,
                "SecondsDetected": 0.0,
                "PercentDetected": 0.0
            },
            "LoadModelSettings": {
                "LoadAtCurrentPosition": true
            },
            "Triggers": {
                "Trigger1": "N3",
                "Trigger2": "",
                "Trigger3": "",
                "ScreenButton": -1
            },
            "IsGlobal": true,
            "IsActive": true,
            "Minimized": false,
            "StopsOnLastFrame": false,
            "DeactivateAfterKeyUp": false,
            "OnlyLoadOneRandomItem": false,
            "DeactivateAfterSeconds": false,
            "DeactivateAfterSecondsAmount": 10.0,
            "FadeSecondsAmount": 0.5,
            "OnScreenHotkeyColor": {
                "r": 1.0,
                "g": 1.0,
                "b": 1.0,
                "a": 1.0
            }
        },
        {
            "HotkeyID": "19b7d9285ad6400ea88cf9221979df57",
            "Name": "",
            "Action": "ToggleExpression",
            "File": "suo.exp3.json",
            "Folder": "",
            "Position": {
                "X": 0.0,
                "Y": 0.0,
                "Z": 0.0,
                "Rotation": 0.0
            },
            "ColorOverlay": {
                "On": false,
                "IsStaticColor": false,
                "Display": -1,
                "WindowName": "",
                "IncludeLeft": false,
                "IncludeMid": false,
                "IncludeRight": false,
                "BaseValue": 0,
                "OverlayValue": 0,
                "Smoothing": 0,
                "IncludeItems": false,
                "StaticColor": {
                    "r": 0.0,
                    "g": 0.0,
                    "b": 0.0,
                    "a": 1.0
                }
            },
            "ColorScreenMultiplyPreset": {
                "ArtMeshMultiplyAndScreenColors": []
            },
            "HandGestureSettings": {
                "GestureLeft": "",
                "GestureRight": "",
                "GestureCombinator": "AND",
                "AllowMirroredGesture": false,
                "DeactivateExpWhenGestureNotDetected": false,
                "SecondsUntilDetection": 0.5,
                "SecondsDetected": 0.0,
                "PercentDetected": 0.0
            },
            "LoadModelSettings": {
                "LoadAtCurrentPosition": true
            },
            "Triggers": {
                "Trigger1": "N4",
                "Trigger2": "",
                "Trigger3": "",
                "ScreenButton": -1
            },
            "IsGlobal": true,
            "IsActive": true,
            "Minimized": false,
            "StopsOnLastFrame": false,
            "DeactivateAfterKeyUp": false,
            "OnlyLoadOneRandomItem": false,
            "DeactivateAfterSeconds": false,
            "DeactivateAfterSecondsAmount": 10.0,
            "FadeSecondsAmount": 0.5,
            "OnScreenHotkeyColor": {
                "r": 1.0,
                "g": 1.0,
                "b": 1.0,
                "a": 1.0
            }
        },
        {
            "HotkeyID": "feaf7b43d60f471c8a3e5afb9b7800dc",
            "Name": "",
            "Action": "ToggleExpression",
            "File": "yun.exp3.json",
            "Folder": "",
            "Position": {
                "X": 0.0,
                "Y": 0.0,
                "Z": 0.0,
                "Rotation": 0.0
            },
            "ColorOverlay": {
                "On": false,
                "IsStaticColor": false,
                "Display": -1,
                "WindowName": "",
                "IncludeLeft": false,
                "IncludeMid": false,
                "IncludeRight": false,
                "BaseValue": 0,
                "OverlayValue": 0,
                "Smoothing": 0,
                "IncludeItems": false,
                "StaticColor": {
                    "r": 0.0,
                    "g": 0.0,
                    "b": 0.0,
                    "a": 1.0
                }
            },
            "ColorScreenMultiplyPreset": {
                "ArtMeshMultiplyAndScreenColors": []
            },
            "HandGestureSettings": {
                "GestureLeft": "",
                "GestureRight": "",
                "GestureCombinator": "AND",
                "AllowMirroredGesture": false,
                "DeactivateExpWhenGestureNotDetected": false,
                "SecondsUntilDetection": 0.5,
                "SecondsDetected": 0.0,
                "PercentDetected": 0.0
            },
            "LoadModelSettings": {
                "LoadAtCurrentPosition": true
            },
            "Triggers": {
                "Trigger1": "N5",
                "Trigger2": "",
                "Trigger3": "",
                "ScreenButton": -1
            },
            "IsGlobal": true,
            "IsActive": true,
            "Minimized": false,
            "StopsOnLastFrame": false,
            "DeactivateAfterKeyUp": false,
            "OnlyLoadOneRandomItem": false,
            "DeactivateAfterSeconds": false,
            "DeactivateAfterSecondsAmount": 10.0,
            "FadeSecondsAmount": 0.5,
            "OnScreenHotkeyColor": {
                "r": 1.0,
                "g": 1.0,
                "b": 1.0,
                "a": 1.0
            }
        },
        {
            "HotkeyID": "217b91c91abb4c929eeea72fa2ae51d6",
            "Name": "",
            "Action": "TriggerAnimation",
            "File": "zhan2.motion3.json",
            "Folder": "",
            "Position": {
                "X": 0.0,
                "Y": 0.0,
                "Z": 0.0,
                "Rotation": 0.0
            },
            "ColorOverlay": {
                "On": false,
                "IsStaticColor": false,
                "Display": -1,
                "WindowName": "",
                "IncludeLeft": false,
                "IncludeMid": false,
                "IncludeRight": false,
                "BaseValue": 0,
                "OverlayValue": 0,
                "Smoothing": 0,
                "IncludeItems": false,
                "StaticColor": {
                    "r": 0.0,
                    "g": 0.0,
                    "b": 0.0,
                    "a": 1.0
                }
            },
            "ColorScreenMultiplyPreset": {
                "ArtMeshMultiplyAndScreenColors": []
            },
            "HandGestureSettings": {
                "GestureLeft": "",
                "GestureRight": "",
                "GestureCombinator": "AND",
                "AllowMirroredGesture": false,
                "DeactivateExpWhenGestureNotDetected": false,
                "SecondsUntilDetection": 0.5,
                "SecondsDetected": 0.0,
                "PercentDetected": 0.0
            },
            "LoadModelSettings": {
                "LoadAtCurrentPosition": true
            },
            "Triggers": {
                "Trigger1": "N6",
                "Trigger2": "",
                "Trigger3": "",
                "ScreenButton": -1
            },
            "IsGlobal": true,
            "IsActive": true,
            "Minimized": false,
            "StopsOnLastFrame": false,
            "DeactivateAfterKeyUp": false,
            "OnlyLoadOneRandomItem": false,
            "DeactivateAfterSeconds": false,
            "DeactivateAfterSecondsAmount": 10.0,
            "FadeSecondsAmount": 0.009999999776482582,
            "OnScreenHotkeyColor": {
                "r": 1.0,
                "g": 1.0,
                "b": 1.0,
                "a": 1.0
            }
        }
    ],
    "HotkeySettings": {
        "UseOnScreenHotkeys": false,
        "UseKeyboardHotkeys": true,
        "SendOnScreenHotkeysToPC": true,
        "OnScreenHotkeyAlpha": 75
    },
    "ArtMeshDetails": {
        "ArtMeshesExcludedFromPinning": [],
        "ArtMeshesThatDeleteItemsOnDrop": [],
        "ArtMeshSceneLightingMultipliers": [],
        "ArtMeshMultiplyAndScreenColors": []
    },
    "ParameterCustomization": {
        "ParametersExcludedFromVNetSmoothing": []
    },
    "PhysicsCustomizationSettings": {
        "PhysicsMultipliersPerPhysicsGroup": [],
        "WindMultipliersPerPhysicsGroup": [],
        "DraggingPhysicsMultipliersPerPhysicsGroup": []
    },
    "FolderInfo": {
        "HotkeyFolders": [],
        "ConfigItemFolders": []
    },
    "SavedActiveExpressions": []
}